phoenix_datasets/__init__.py
phoenix_datasets/corpora.py
phoenix_datasets/datasets.py
phoenix_datasets/utils.py
phoenix_datasets-0.0.1.dev0.dist-info/LICENSE
phoenix_datasets-0.0.1.dev0.dist-info/METADATA
phoenix_datasets-0.0.1.dev0.dist-info/WHEEL
phoenix_datasets-0.0.1.dev0.dist-info/top_level.txt
phoenix_datasets-0.0.1.dev0.dist-info/RECORD
