Metadata-Version: 2.1
Name: phoenix-datasets
Version: 0.0.1.dev0
Summary: PyTorch dataset wrappers for PHOENIX 2014 & PHOENIX-2014-T sign language datasets.
Home-page: https://github.com/enhuiz/phoenix_datasets
Author: enhuiz
Author-email: niuzhe.nz@outlook.com
License: UNKNOWN
Platform: UNKNOWN
Requires-Python: >=3.6.0
Requires-Dist: pandas
Requires-Dist: numpy
Requires-Dist: torch
Requires-Dist: torchvision
Requires-Dist: pandarallel
